dbbackup/__init__.py
dbbackup/apps.py
dbbackup/checks.py
dbbackup/log.py
dbbackup/settings.py
dbbackup/signals.py
dbbackup/storage.py
dbbackup/utils.py
dbbackup/db/__init__.py
dbbackup/db/base.py
dbbackup/db/django.py
dbbackup/db/exceptions.py
dbbackup/db/mongodb.py
dbbackup/db/mysql.py
dbbackup/db/postgresql.py
dbbackup/db/sqlite.py
dbbackup/management/__init__.py
dbbackup/management/commands/__init__.py
dbbackup/management/commands/_base.py
dbbackup/management/commands/dbbackup.py
dbbackup/management/commands/dbrestore.py
dbbackup/management/commands/listbackups.py
dbbackup/management/commands/mediabackup.py
dbbackup/management/commands/mediarestore.py
django_dbbackup-5.1.1.dist-info/METADATA
django_dbbackup-5.1.1.dist-info/WHEEL
django_dbbackup-5.1.1.dist-info/licenses/LICENSE.md
django_dbbackup-5.1.1.dist-info/RECORD
